faas/__init__.py
faas/context/__init__.py
faas/context/model.py
faas/context/observer/__init__.py
faas/context/observer/api.py
faas/context/platform/__init__.py
faas/context/platform/deployment/__init__.py
faas/context/platform/deployment/api.py
faas/context/platform/deployment/inmemory.py
faas/context/platform/network/__init__.py
faas/context/platform/network/api.py
faas/context/platform/network/inmemory.py
faas/context/platform/node/__init__.py
faas/context/platform/node/api.py
faas/context/platform/node/inmemory.py
faas/context/platform/replica/__init__.py
faas/context/platform/replica/api.py
faas/context/platform/replica/inmemory.py
faas/context/platform/telemetry/__init__.py
faas/context/platform/telemetry/api.py
faas/context/platform/trace/__init__.py
faas/context/platform/trace/api.py
faas/context/platform/trace/inmemory.py
faas/context/platform/zone/__init__.py
faas/context/platform/zone/api.py
faas/context/platform/zone/inmemory.py
faas/opt/__init__.py
faas/opt/api.py
faas/opt/reconciled.py
faas/system/__init__.py
faas/system/core.py
faas/system/exception.py
faas/system/loadbalancer.py
faas/system/metric.py
faas/util/__init__.py
faas/util/constant.py
faas/util/point.py
faas/util/rwlock.py
edgerun_faas-0.0.1.dev6.dist-info/LICENSE
edgerun_faas-0.0.1.dev6.dist-info/METADATA
edgerun_faas-0.0.1.dev6.dist-info/WHEEL
edgerun_faas-0.0.1.dev6.dist-info/top_level.txt
edgerun_faas-0.0.1.dev6.dist-info/RECORD
