Metadata-Version: 2.1
Name: edgerun-faas
Version: 0.0.1.dev6
Summary: Edgerun FaaS
Home-page: https://github.com/edgerun/faas
Author: Philipp Raith, Thomas Rausch
Author-email: p.raith@dsg.tuwien.ac.at, t.rausch@dsg.tuwien.ac.at
License: UNKNOWN
Platform: UNKNOWN
Classifier: Programming Language :: Python :: 3
Classifier: Operating System :: OS Independent
License-File: LICENSE
Requires-Dist: pandas (>=1.2.5)
Requires-Dist: readerwriterlock (==1.0.9)
Requires-Dist: dataclasses-json (==0.5.7)
